pdbmender/__init__.py
pdbmender/addHtaut
pdbmender/constants.py
pdbmender/ffconverter.py
pdbmender/formats.py
pdbmender/pdb2pqr/.htaccess
pdbmender/pdb2pqr/.sconsign.dblite
pdbmender/pdb2pqr/.variables.cache
pdbmender/pdb2pqr/AUTHORS
pdbmender/pdb2pqr/AppService_client.py
pdbmender/pdb2pqr/AppService_services.py
pdbmender/pdb2pqr/AppService_services_types.py
pdbmender/pdb2pqr/AppService_types.py
pdbmender/pdb2pqr/BINARY_README.md
pdbmender/pdb2pqr/COPYING
pdbmender/pdb2pqr/ChangeLog.md
pdbmender/pdb2pqr/INSTALL.md
pdbmender/pdb2pqr/NEWS
pdbmender/pdb2pqr/README.md
pdbmender/pdb2pqr/SConscript-error.py
pdbmender/pdb2pqr/SConscript-install.py
pdbmender/pdb2pqr/SConscript-main.py
pdbmender/pdb2pqr/SConstruct
pdbmender/pdb2pqr/ServerNotes.md
pdbmender/pdb2pqr/apbs_cgi.cgi
pdbmender/pdb2pqr/apbs_cgi.py
pdbmender/pdb2pqr/build_config.py
pdbmender/pdb2pqr/conf_avg/Ensemble_phimap.py
pdbmender/pdb2pqr/conf_avg/Gromacs_class.py
pdbmender/pdb2pqr/conf_avg/phimap_class.py
pdbmender/pdb2pqr/dat/AA.xml
pdbmender/pdb2pqr/dat/AMBER.DAT
pdbmender/pdb2pqr/dat/AMBER.names
pdbmender/pdb2pqr/dat/CHARMM.DAT
pdbmender/pdb2pqr/dat/CHARMM.names
pdbmender/pdb2pqr/dat/GROMOS.DAT
pdbmender/pdb2pqr/dat/GROMOS.names
pdbmender/pdb2pqr/dat/GROMOS_PRO.names
pdbmender/pdb2pqr/dat/GROMOS_PROT.DAT
pdbmender/pdb2pqr/dat/GROMOS_RNA.DAT
pdbmender/pdb2pqr/dat/GROMOS_RNA.names
pdbmender/pdb2pqr/dat/HYDROGENS.xml
pdbmender/pdb2pqr/dat/NA.xml
pdbmender/pdb2pqr/dat/PARSE.DAT
pdbmender/pdb2pqr/dat/PARSE.names
pdbmender/pdb2pqr/dat/PATCHES.xml
pdbmender/pdb2pqr/dat/PEOEPB.DAT
pdbmender/pdb2pqr/dat/PEOEPB.names
pdbmender/pdb2pqr/dat/RNA.DAT
pdbmender/pdb2pqr/dat/RNA.names
pdbmender/pdb2pqr/dat/SWANSON.DAT
pdbmender/pdb2pqr/dat/SWANSON.names
pdbmender/pdb2pqr/dat/TOPOLOGY.xml
pdbmender/pdb2pqr/dat/TYL06.DAT
pdbmender/pdb2pqr/dat/TYL06.names
pdbmender/pdb2pqr/dx2cube.py
pdbmender/pdb2pqr/extensions/README
pdbmender/pdb2pqr/extensions/__init__.py
pdbmender/pdb2pqr/extensions/chi.py
pdbmender-0.6.1.dist-info/WHEEL
pdbmender-0.6.1.dist-info/METADATA
pdbmender-0.6.1.dist-info/RECORD
