Metadata-Version: 2.1
Name: pdbmender
Version: 0.6.1
Summary: Mend PDB files
License: MIT
Author: Pedro B.P.S. Reis
Author-email: pdreis@fc.ul.pt
Requires-Python: >=3.6,<4.0
Classifier: License :: OSI Approved :: MIT License
Classifier: Programming Language :: Python :: 3
Classifier: Programming Language :: Python :: 3.10
Classifier: Programming Language :: Python :: 3.6
Classifier: Programming Language :: Python :: 3.7
Classifier: Programming Language :: Python :: 3.8
Classifier: Programming Language :: Python :: 3.9
